cite_runner/__init__.py
cite_runner/__main__.py
cite_runner/config.py
cite_runner/exceptions.py
cite_runner/main.py
cite_runner/models.py
cite_runner/teamengine_runner.py
cite_runner/parsers/__init__.py
cite_runner/parsers/earl.py
cite_runner/serializers/__init__.py
cite_runner/serializers/console.py
cite_runner/serializers/simple.py
cite_runner/templates/test-suite-result.md
cite_runner-0.2.0.dist-info/METADATA
cite_runner-0.2.0.dist-info/WHEEL
cite_runner-0.2.0.dist-info/entry_points.txt
cite_runner-0.2.0.dist-info/licenses/LICENSE
cite_runner-0.2.0.dist-info/RECORD
